{
  "identifier": "migrated",
  "description": "permissions that were migrated from v1",
  "local": true,
  "windows": [
    "main"
  ],
  "permissions": [
    "core:default",
    "core:path:default",
    "shell:allow-open",
    "shell:default",
    "stronghold:default",
    "stronghold:allow-initialize",
    "stronghold:allow-create-client",
    "stronghold:allow-load-client",
    "stronghold:allow-destroy",
    "stronghold:allow-save",
    "stronghold:allow-save-secret",
    "stronghold:allow-execute-procedure",
    "stronghold:allow-get-store-record",
    "stronghold:allow-save-store-record",
    "stronghold:allow-remove-store-record"
  ]
}